lofi_gen/__init__.py
lofi_gen/music/__init__.py
lofi_gen/music/audio.py
lofi_gen/music/generator.py
lofi_gen/music/registry.py
lofi_gen/music/models/__init__.py
lofi_gen/music/models/base.py
lofi_gen/music/models/custom_midi_generator.py
lofi_gen/music/models/musicgen.py
lofi_gen/music/pipelines/__init__.py
lofi_gen/music/pipelines/long_music_gen.py
lofi_gen-0.1.0.dist-info/licenses/LICENSE
lofi_gen-0.1.0.dist-info/METADATA
lofi_gen-0.1.0.dist-info/WHEEL
lofi_gen-0.1.0.dist-info/top_level.txt
lofi_gen-0.1.0.dist-info/RECORD
