Metadata-Version: 2.4
Name: lofi-gen
Version: 0.1.0
Summary: A Python package for generating Lofi music using AI models
Author-email: Nikesh Gyawali <gnikesh03@gmail.com>
License: MIT License
Project-URL: Homepage, https://github.com/gnikesh/lofi-gen
Project-URL: Repository, https://github.com/gnikesh/lofi-gen
Project-URL: Issues, https://github.com/gnikesh/lofi-gen/issues
Keywords: music-generation,lofi,ai,audio,musicgen
Classifier: Development Status :: 3 - Alpha
Classifier: Intended Audience :: Developers
Classifier: Intended Audience :: Science/Research
Classifier: License :: OSI Approved :: MIT License
Classifier: Programming Language :: Python :: 3
Classifier: Programming Language :: Python :: 3.8
Classifier: Programming Language :: Python :: 3.9
Classifier: Programming Language :: Python :: 3.10
Classifier: Programming Language :: Python :: 3.11
Classifier: Topic :: Multimedia :: Sound/Audio
Classifier: Topic :: Multimedia :: Sound/Audio :: Analysis
Classifier: Topic :: Scientific/Engineering :: Artificial Intelligence
Requires-Python: >=3.8
License-File: LICENSE
Requires-Dist: torch>=2.0.0
Requires-Dist: transformers>=4.30.0
Requires-Dist: numpy>=1.21.0
Requires-Dist: scipy>=1.7.0
Requires-Dist: librosa>=0.10.0
Requires-Dist: soundfile>=0.12.0
Provides-Extra: dev
Requires-Dist: pytest>=7.0.0; extra == "dev"
Requires-Dist: pytest-cov>=4.0.0; extra == "dev"
Requires-Dist: black>=23.0.0; extra == "dev"
Requires-Dist: flake8>=6.0.0; extra == "dev"
Requires-Dist: mypy>=1.0.0; extra == "dev"
Provides-Extra: midi
Requires-Dist: midiutil>=1.2.1; extra == "midi"
Requires-Dist: pydub>=0.25.0; extra == "midi"
Provides-Extra: all
Requires-Dist: lofi-gen[dev,midi]; extra == "all"
Dynamic: license-file
